[
  {
    "name": "reddit_get_post",
    "description": "Get a Reddit post by ID",
    "arguments": [
      {
        "name": "id",
        "type": "string",
        "desc": "Post ID (with or without t3_ prefix)"
      }
    ]
  },
  {
    "name": "reddit_get_comments",
    "description": "Get comments for a post with nested replies",
    "arguments": [
      {
        "name": "post_id",
        "type": "string",
        "desc": "Post ID to get comments from"
      },
      {
        "name": "sort",
        "type": "string",
        "desc": "Sort order: confidence, top, new, controversial, old, random, qa"
      },
      {
        "name": "limit",
        "type": "number",
        "desc": "Maximum number of comments to retrieve (default: 100)"
      }
    ]
  },
  {
    "name": "reddit_search_posts",
    "description": "Search for posts across Reddit or within a subreddit",
    "arguments": [
      {
        "name": "query",
        "type": "string",
        "desc": "Search query string"
      },
      {
        "name": "subreddit",
        "type": "string",
        "desc": "Limit search to specific subreddit (optional)"
      },
      {
        "name": "sort",
        "type": "string",
        "desc": "Sort order: relevance, hot, top, new, comments"
      },
      {
        "name": "time",
        "type": "string",
        "desc": "Time filter: all, hour, day, week, month, year"
      },
      {
        "name": "limit",
        "type": "number",
        "desc": "Maximum results (default: 25)"
      }
    ]
  },
  {
    "name": "reddit_get_subreddit_posts",
    "description": "Get posts from a subreddit",
    "arguments": [
      {
        "name": "subreddit",
        "type": "string",
        "desc": "Subreddit name"
      },
      {
        "name": "sort",
        "type": "string",
        "desc": "Sort order: hot, new, rising, top, controversial"
      },
      {
        "name": "time",
        "type": "string",
        "desc": "Time filter for top/controversial: all, hour, day, week, month, year"
      },
      {
        "name": "limit",
        "type": "number",
        "desc": "Maximum posts to retrieve (default: 25)"
      }
    ]
  },
  {
    "name": "reddit_get_subreddit_info",
    "description": "Get information about a subreddit",
    "arguments": [
      {
        "name": "subreddit",
        "type": "string",
        "desc": "Subreddit name"
      }
    ]
  },
  {
    "name": "reddit_get_user_content",
    "description": "Get posts and comments from a user",
    "arguments": [
      {
        "name": "username",
        "type": "string",
        "desc": "Reddit username"
      },
      {
        "name": "content_type",
        "type": "string",
        "desc": "Type of content: overview, submitted, comments"
      },
      {
        "name": "sort",
        "type": "string",
        "desc": "Sort order: new, hot, top, controversial"
      },
      {
        "name": "time",
        "type": "string",
        "desc": "Time filter: all, hour, day, week, month, year"
      },
      {
        "name": "limit",
        "type": "number",
        "desc": "Maximum items to retrieve (default: 25)"
      }
    ]
  },
  {
    "name": "reddit_submit_post",
    "description": "Submit a new post to a subreddit",
    "arguments": [
      {
        "name": "subreddit",
        "type": "string",
        "desc": "Subreddit to post to"
      },
      {
        "name": "title",
        "type": "string",
        "desc": "Post title"
      },
      {
        "name": "text",
        "type": "string",
        "desc": "Post body text (for text posts)"
      },
      {
        "name": "url",
        "type": "string",
        "desc": "URL (for link posts)"
      },
      {
        "name": "nsfw",
        "type": "boolean",
        "desc": "Mark as NSFW"
      },
      {
        "name": "spoiler",
        "type": "boolean",
        "desc": "Mark as spoiler"
      }
    ]
  },
  {
    "name": "reddit_submit_comment",
    "description": "Submit a comment on a post or reply to another comment",
    "arguments": [
      {
        "name": "parent",
        "type": "string",
        "desc": "Parent ID (post or comment ID with t1_/t3_ prefix)"
      },
      {
        "name": "text",
        "type": "string",
        "desc": "Comment text (markdown supported)"
      }
    ]
  },
  {
    "name": "reddit_edit_content",
    "description": "Edit your own post or comment",
    "arguments": [
      {
        "name": "id",
        "type": "string",
        "desc": "Content ID (with t1_/t3_ prefix)"
      },
      {
        "name": "text",
        "type": "string",
        "desc": "New text content"
      }
    ]
  },
  {
    "name": "reddit_delete_content",
    "description": "Delete your own post or comment",
    "arguments": [
      {
        "name": "id",
        "type": "string",
        "desc": "Content ID to delete (with t1_/t3_ prefix)"
      }
    ]
  },
  {
    "name": "reddit_vote",
    "description": "Vote on a post or comment",
    "arguments": [
      {
        "name": "id",
        "type": "string",
        "desc": "Content ID (with t1_/t3_ prefix)"
      },
      {
        "name": "dir",
        "type": "number",
        "desc": "Vote direction: 1 (upvote), 0 (unvote), -1 (downvote)"
      }
    ]
  },
  {
    "name": "reddit_save",
    "description": "Save a post or comment",
    "arguments": [
      {
        "name": "id",
        "type": "string",
        "desc": "Content ID to save (with t1_/t3_ prefix)"
      }
    ]
  },
  {
    "name": "reddit_unsave",
    "description": "Unsave a post or comment",
    "arguments": [
      {
        "name": "id",
        "type": "string",
        "desc": "Content ID to unsave (with t1_/t3_ prefix)"
      }
    ]
  }
]
